{
  "$schema": "https://schema.tauri.app/config/2",
  "productName": "Annas Browser",
  "version": "1.0.0",
  "identifier": "com.annas.browser",
  "build": {
    "beforeDevCommand": "",
    "beforeBuildCommand": "",
    "devUrl": "http://localhost:1420",
    "frontendDist": "../dist"
  },
  "app": {
    "windows": [
      {
        "title": "Annas Browser",
        "width": 1280,
        "height": 800,
        "url": "index.html"
      }
    ],
    "security": {
      "csp": null
    }
  },
  "bundle": {
    "active": true,
    "targets": "all",
    "icon": []
  }
}
